pymymodeler/__init__.py
pymymodeler/engines.py
pymymodeler/gen_pydantic_model.py
pymymodeler/gen_sql_model.py
pymymodeler-0.1.2.dist-info/LICENSE
pymymodeler-0.1.2.dist-info/METADATA
pymymodeler-0.1.2.dist-info/WHEEL
pymymodeler-0.1.2.dist-info/top_level.txt
pymymodeler-0.1.2.dist-info/RECORD
