Metadata-Version: 2.1
Name: pymymodeler
Version: 0.1.2
Summary: A library to generate SQLAlchemy and Pydantic models from MySQL databases
Author-email: masoppubun <spice.alone@gmail.com>
License: MIT
Project-URL: Homepage, https://github.com/masoppubun/pymymodeler
Classifier: Development Status :: 3 - Alpha
Classifier: Intended Audience :: Developers
Classifier: License :: OSI Approved :: MIT License
Classifier: Programming Language :: Python :: 3
Classifier: Programming Language :: Python :: 3.10
Classifier: Programming Language :: Python :: 3.11
Classifier: Programming Language :: Python :: 3.12
Requires-Python: >=3.8
License-File: LICENSE
Requires-Dist: sqlalchemy>=2.0
Requires-Dist: pydantic>=2.0
Requires-Dist: pymysql>=1.0
Requires-Dist: sqlacodegen-v2>=0.1
